avantpy_trans/curses/__init__.py
avantpy_trans/curses/ga.yaml
avantpy_trans.curses-0.0.2.dist-info/WHEEL
avantpy_trans.curses-0.0.2.dist-info/METADATA
avantpy_trans.curses-0.0.2.dist-info/RECORD
